colcon_meson/__init__.py
colcon_meson/build.py
colcon_meson/identification.py
colcon_meson-0.5.0.dist-info/licenses/LICENSE
colcon_meson-0.5.0.dist-info/METADATA
colcon_meson-0.5.0.dist-info/WHEEL
colcon_meson-0.5.0.dist-info/entry_points.txt
colcon_meson-0.5.0.dist-info/top_level.txt
colcon_meson-0.5.0.dist-info/RECORD
