Metadata-Version: 2.4
Name: colcon-meson
Version: 0.5.0
Summary: Extension for colcon to support Meson packages.
Author: Christian Rauch
Author-email: Rauch.Christian@gmx.de
Maintainer: Christian Rauch
Maintainer-email: Rauch.Christian@gmx.de
License: Apache License, Version 2.0
Project-URL: GitHub, https://github.com/colcon/colcon-meson
Keywords: colcon
Requires-Python: >=3.6
License-File: LICENSE
Requires-Dist: colcon-core>=0.10.0
Requires-Dist: colcon-library-path
Requires-Dist: meson>=0.60.0
Provides-Extra: test
Requires-Dist: flake8<6,>=3.6.0; extra == "test"
Requires-Dist: flake8-blind-except; extra == "test"
Requires-Dist: flake8-builtins; extra == "test"
Requires-Dist: flake8-class-newline; extra == "test"
Requires-Dist: flake8-comprehensions; extra == "test"
Requires-Dist: flake8-deprecated; extra == "test"
Requires-Dist: flake8-docstrings; extra == "test"
Requires-Dist: flake8-import-order; extra == "test"
Requires-Dist: flake8-quotes; extra == "test"
Requires-Dist: pep8-naming; extra == "test"
Requires-Dist: pylint; extra == "test"
Requires-Dist: pytest; extra == "test"
Requires-Dist: pytest-cov; extra == "test"
Requires-Dist: scspell3k>=2.2; extra == "test"
Dynamic: license-file
